calculadorafabeliz/__init__.py
calculadorafabeliz/basicOperations.py
calculadorafabeliz/mathOperations.py
calculator_fabeliz-0.0.1.dist-info/LICENSE
calculator_fabeliz-0.0.1.dist-info/METADATA
calculator_fabeliz-0.0.1.dist-info/WHEEL
calculator_fabeliz-0.0.1.dist-info/top_level.txt
calculator_fabeliz-0.0.1.dist-info/RECORD
