Metadata-Version: 2.1
Name: calculator-fabeliz
Version: 0.0.1
Summary: Calculadora Matematica / Math Calculator
Author: Fabeliz Irene Alvarez Salazar
Author-email: irenex2018@gmail.com
License-File: LICENSE
